WizardVsWorld/__init__.py
WizardVsWorld/assets/__init__.py
WizardVsWorld/assets/archer.png
WizardVsWorld/assets/archerattack.png
WizardVsWorld/assets/archerattackable.png
WizardVsWorld/assets/archerhurt.png
WizardVsWorld/assets/arrow.png
WizardVsWorld/assets/background.png
WizardVsWorld/assets/backgroundSMALL.png
WizardVsWorld/assets/bush.png
WizardVsWorld/assets/bushFIRE.png
WizardVsWorld/assets/bushORANGE.png
WizardVsWorld/assets/bushRED.png
WizardVsWorld/assets/cactus.png
WizardVsWorld/assets/cactusFIRE.png
WizardVsWorld/assets/cactusORANGE.png
WizardVsWorld/assets/cactusRED.png
WizardVsWorld/assets/darkbrick.png
WizardVsWorld/assets/darkbrickORANGE.png
WizardVsWorld/assets/darkbrickRED.png
WizardVsWorld/assets/darkfireball.PNG
WizardVsWorld/assets/dirt.png
WizardVsWorld/assets/dirtBLUE.png
WizardVsWorld/assets/dirtFIRE.png
WizardVsWorld/assets/dirtORANGE.png
WizardVsWorld/assets/dirtRED.png
WizardVsWorld/assets/floor.png
WizardVsWorld/assets/floorBLUE.png
WizardVsWorld/assets/floorFIRE.png
WizardVsWorld/assets/floorORANGE.png
WizardVsWorld/assets/floorRED.png
WizardVsWorld/assets/grass.png
WizardVsWorld/assets/grassBLUE.png
WizardVsWorld/assets/grassFIRE.png
WizardVsWorld/assets/grassORANGE.png
WizardVsWorld/assets/grassRED.png
WizardVsWorld/assets/greatknight.png
WizardVsWorld/assets/greatknightattack.png
WizardVsWorld/assets/greatknighthurt.png
WizardVsWorld/assets/greatmarksman.png
WizardVsWorld/assets/greatmarksmanattack.png
WizardVsWorld/assets/greatmarksmanhurt.png
WizardVsWorld/assets/image_loader.py
WizardVsWorld/assets/knight.png
WizardVsWorld/assets/knightattack.png
WizardVsWorld/assets/knightattackable.png
WizardVsWorld/assets/knighthurt.png
WizardVsWorld/assets/logo.png
WizardVsWorld/assets/marksmanarrow.png
WizardVsWorld/assets/mud.png
WizardVsWorld/assets/mudBLUE.png
WizardVsWorld/assets/mudFIRE.png
WizardVsWorld/assets/mudORANGE.png
WizardVsWorld/assets/mudRED.png
WizardVsWorld/assets/mudbrick.png
WizardVsWorld/assets/mudbrickORANGE.png
WizardVsWorld-1.0.3.dist-info/LICENSE
WizardVsWorld-1.0.3.dist-info/METADATA
WizardVsWorld-1.0.3.dist-info/WHEEL
WizardVsWorld-1.0.3.dist-info/entry_points.txt
WizardVsWorld-1.0.3.dist-info/top_level.txt
WizardVsWorld-1.0.3.dist-info/RECORD
