Metadata-Version: 2.1
Name: WizardVsWorld
Version: 1.0.3
Summary: 2D tactical game involving magic and malice.
Home-page: https://github.com/lukeherczeg/WizardvsWorld
Author: Logan D.G. Smith
Author-email: loganda.smith@ufl.edu
License: UNKNOWN
Platform: UNKNOWN
Classifier: Programming Language :: Python :: 3
Classifier: License :: OSI Approved :: MIT License
Classifier: Operating System :: OS Independent
Requires-Python: >=3.7, <3.8
Requires-Dist: pygame (==1.9.6)
